flask_request_data_normalizer/NormalizedRequest.py
flask_request_data_normalizer/RequestDataNormalizer.py
flask_request_data_normalizer/__init__.py
Flask_RDN-1.0.4.dist-info/LICENSE
Flask_RDN-1.0.4.dist-info/METADATA
Flask_RDN-1.0.4.dist-info/WHEEL
Flask_RDN-1.0.4.dist-info/top_level.txt
Flask_RDN-1.0.4.dist-info/RECORD
