Metadata-Version: 2.1
Name: Flask-RDN
Version: 1.0.4
Summary: Streamline and supercharge your query string parameter parsing in Flask!
Home-page: https://github.com/Topazoo/Flask-Request-Data-Normalizer
Maintainer: Peter Swanson
Project-URL: Bug Tracker, https://github.com/Topazoo/Flask-Request-Data-Normalizer/issues
Project-URL: Changelog, https://github.com/Topazoo/Flask-Request-Data-Normalizer/releases
Classifier: Programming Language :: Python :: 3
Classifier: License :: OSI Approved :: BSD License
Classifier: Intended Audience :: Developers
License-File: LICENSE
Requires-Dist: Flask >=2.0.3
Requires-Dist: Query-String-Manager >=1.0.10
